{
	"name": "SQL script 2",
	"properties": {
		"content": {
			"query": "-- This is auto-generated code\nSELECT TOP 100\n*\nFROM\n    OPENROWSET(\n        BULK 'https://nycanalyticsmarlabsdl.dfs.core.windows.net/nyc-taxi-data/raw/payment_type_array.json',\n        FORMAT = 'CSV',\n        FIELDQUOTE = '0x0b',\n        FIELDTERMINATOR ='0x0b',\n        ROWTERMINATOR = '0x0b'\n    )\n    WITH (\n        jsonContent varchar(MAX)\n    ) AS [result]\n    CROSS APPLY OPENJSON(jsonContent)\n    WITH\n    (\n        rate_code_id SMALLINT,\n        rate_code VARCHAR(30)\n    );\n\n",
			"metadata": {
				"language": "sql"
			},
			"currentConnection": {
				"databaseName": "master",
				"poolName": "Built-in"
			},
			"resultLimit": 5000
		},
		"type": "SqlQuery"
	}
}